llama_index_client/__init__.py
llama_index_client/client.py
llama_index_client/core/__init__.py
llama_index_client/core/api_error.py
llama_index_client/core/client_wrapper.py
llama_index_client/core/datetime_utils.py
llama_index_client/core/jsonable_encoder.py
llama_index_client/core/remove_none_from_dict.py
llama_index_client/errors/__init__.py
llama_index_client/errors/unprocessable_entity_error.py
llama_index_client/resources/__init__.py
llama_index_client/resources/api_key/__init__.py
llama_index_client/resources/api_key/client.py
llama_index_client/resources/component_definition/__init__.py
llama_index_client/resources/component_definition/client.py
llama_index_client/resources/data_sink/__init__.py
llama_index_client/resources/data_sink/client.py
llama_index_client/resources/data_sink/types/__init__.py
llama_index_client/resources/data_sink/types/data_sink_update_component.py
llama_index_client/resources/data_sink/types/data_sink_update_component_one.py
llama_index_client/resources/data_source/__init__.py
llama_index_client/resources/data_source/client.py
llama_index_client/resources/data_source/types/__init__.py
llama_index_client/resources/data_source/types/data_source_update_component.py
llama_index_client/resources/data_source/types/data_source_update_component_one.py
llama_index_client/resources/eval/__init__.py
llama_index_client/resources/eval/client.py
llama_index_client/resources/health/__init__.py
llama_index_client/resources/health/client.py
llama_index_client/resources/parsing/__init__.py
llama_index_client/resources/parsing/client.py
llama_index_client/resources/pipeline/__init__.py
llama_index_client/resources/pipeline/client.py
llama_index_client/resources/project/__init__.py
llama_index_client/resources/project/client.py
llama_index_client/types/__init__.py
llama_index_client/types/api_key.py
llama_index_client/types/azure_open_ai_embedding.py
llama_index_client/types/base_prompt_template.py
llama_index_client/types/base_pydantic_reader.py
llamaindex_py_client-0.1.12.dist-info/LICENSE
llamaindex_py_client-0.1.12.dist-info/METADATA
llamaindex_py_client-0.1.12.dist-info/WHEEL
llamaindex_py_client-0.1.12.dist-info/RECORD
