Metadata-Version: 2.1
Name: llamaindex-py-client
Version: 0.1.12
Summary: 
Author: Logan Markewich
Author-email: logan@runllama.ai
Requires-Python: >=3.8,<4.0
Classifier: Programming Language :: Python :: 3
Classifier: Programming Language :: Python :: 3.8
Classifier: Programming Language :: Python :: 3.9
Classifier: Programming Language :: Python :: 3.10
Classifier: Programming Language :: Python :: 3.11
Requires-Dist: httpx (>=0.20.0)
Requires-Dist: pydantic (>=1.10)
